wmul_rivendell/DatabaseStatistics.py
wmul_rivendell/FilterCartReportForMusicScheduler.py
wmul_rivendell/LoadCartDataDump.py
wmul_rivendell/LoadCurrentLogLine.py
wmul_rivendell/RivendellAudioImporter.py
wmul_rivendell/__init__.py
wmul_rivendell/cli.py
wmul_rivendell-0.14.0.dist-info/entry_points.txt
wmul_rivendell-0.14.0.dist-info/LICENSE
wmul_rivendell-0.14.0.dist-info/WHEEL
wmul_rivendell-0.14.0.dist-info/METADATA
wmul_rivendell-0.14.0.dist-info/RECORD
