Metadata-Version: 2.3
Name: wmul_rivendell
Version: 0.14.0
Summary: Various scripts to help use Rivendell Radio Automation 4+
Author-email: Michael Stanley <stanley50@marshall.edu>
Classifier: Programming Language :: Python :: 3
Classifier: License :: OSI Approved :: GNU General Public License v3 (GPLv3)
Classifier: Operating System :: OS Independent
Classifier: Development Status :: 5 - Production/Stable
Requires-Dist: wmul_logger>=0.5.1
Requires-Dist: wmul_emailer>=0.5.0
Requires-Dist: click
Requires-Dist: mysql-connector-python>8.0
Requires-Dist: cachetools
Requires-Dist: protobuf>=3.19.0
Requires-Dist: numpy
Requires-Dist: pandas
Requires-Dist: openpyxl
Requires-Dist: pydantic
Requires-Dist: pytest ; extra == "test"
Requires-Dist: pytest-mock ; extra == "test"
Requires-Dist: pyfakefs ; extra == "test"
Requires-Dist: wmul_test_utils>=0.3.1 ; extra == "test"
Requires-Dist: tox ; extra == "tox"
Project-URL: Bug Tracker, https://github.com/MikeTheHammer/wmul_rivendell/issues
Project-URL: Home, https://github.com/MikeTheHammer/wmul_rivendell
Provides-Extra: test
Provides-Extra: tox
